[
  {
    "genes": [
      122,
      118,
      45,
      105,
      51,
      13
    ],
    "perfiles": [
      "ORC 305 x 15.9",
      "ORC 254 x 15.9",
      "IR 254 x 67.0",
      "ORC 152 x 15.9",
      "ORC 76 x 6.4",
      "IR 203 x 26.8"
    ],
    "peso_kg": 71584.01750959814,
    "constructibilidad": {
      "lrfd_local": 0.0,
      "columna_mismo_perfil_altura": 0.0,
      "telescopico": 0.0,
      "ancho_nudo": 0.0,
      "total": 0.0
    },
    "penal_constructibilidad": 0.0,
    "penal_constructibilidad_letal": 0.0,
    "penal_embudo": 0.0,
    "guillotina": false,
    "fitness": [
      71584.01750959814,
      0.0010918951205383849,
      0.12335028497166003
    ],
    "metricas": {
      "max_dc": 0.7735649309222661,
      "max_dc_combo": "GRAV_DISEÑO",
      "max_dc_elemento": 430,
      "max_dc_extremo": "envolvente",
      "max_dc_tipo_revision": "flexion_escalar_viga",
      "max_dc_pu_N": 0.0,
      "max_dc_muy_Nm": 66978.87095881386,
      "max_dc_muz_Nm": 1.3500065079502175e-13,
      "max_dc_phi_pn_N": 0.0,
      "max_dc_phi_mny_Nm": 86584.67865,
      "max_dc_phi_mnz_Nm": 86584.67865,
      "max_dc_ratio_axial": 0.0,
      "max_dc_ratio_my": 0.7735649309222661,
      "max_dc_ratio_mz": 0.0,
      "max_dc_rama": "",
      "objetivo_dc_meta_util": 0.8,
      "objetivo_dc_max_util": 0.95,
      "cumple_objetivo_dc_max": true,
      "exceso_objetivo_dc": 0.0,
      "objetivo_dc_equilibrio": 0.0010918951205383849,
      "max_deriva_elastica": 0.0006294543334768043,
      "max_deriva_combo": "SISMO_DOWN_1",
      "max_deriva_nivel": "Nivel 9.600000000000001 m",
      "util_servicio": 0.12589086669536087,
      "util_colapso": 0.2797574815452464,
      "desp_azotea_m": 0.005102927554130818,
      "desp_azotea_combo": "SISMO_DOWN_1",
      "util_azotea": 0.05102927554130818,
      "util_deriva": 0.2797574815452464,
      "objetivo_deriva_modo": "auto",
      "sistema_lateral": "arriostrado",
      "objetivo_deriva_min_util": 0.25,
      "objetivo_deriva_meta_util": 0.35,
      "cumple_objetivo_deriva_min": true,
      "deficit_objetivo_deriva": 0.0,
      "objetivo_deriva_equilibrio": 0.12335028497166003,
      "util_esbeltez": 0.16555944354537128,
      "esbeltez_elemento": 306,
      "esbeltez_kl_r": 33.11188870907426,
      "factor_cortante": 1.0,
      "factor_cortante_combo": "",
      "factor_cortante_direccion": "",
      "cortante_invalido": 0.0,
      "lrfd_detallado_activo": true,
      "lrfd_detallado_modo": "completo",
      "cumple_lrfd_detallado": true,
      "lrfd_max_util": 0.7933926972947388,
      "lrfd_penalizacion": 0.0,
      "lrfd_error": "",
      "lrfd_vigas_ir_total": 152,
      "lrfd_vigas_ir_no_cumplen": 0,
      "lrfd_vigas_ir_util_max": 0.7933926972947388,
      "lrfd_vigas_ir_elemento_critico": 430,
      "lrfd_vigas_ir_grupo_critico": "Viga_2",
      "lrfd_vigas_ir_perfil_critico": "IR 203 x 26.8",
      "lrfd_vigas_ir_estado_limite": "PLT",
      "lrfd_vigas_ir_mu_kN_m": 66.97887095881386,
      "lrfd_vigas_ir_mr_kN_m": 84.42083118132327,
      "lrfd_columnas_or_total": 64,
      "lrfd_columnas_or_no_cumplen": 0,
      "lrfd_columnas_or_util_max": 0.35097039228617793,
      "lrfd_columnas_or_interaccion_max": 0.35097039228617793,
      "lrfd_columnas_or_elemento_critico": 106,
      "lrfd_columnas_or_grupo_critico": "Columna_2",
      "lrfd_columnas_or_perfil_critico": "ORC 254 x 15.9",
      "lrfd_columnas_or_combo_critico": "GRAV_DISEÑO",
      "lrfd_contravientos_or_total": 64,
      "lrfd_contravientos_or_no_cumplen": 0,
      "lrfd_contravientos_or_util_max": 0.6482334172405333,
      "lrfd_contravientos_or_elemento_critico": 367,
      "lrfd_contravientos_or_grupo_critico": "Contraviento_2",
      "lrfd_contravientos_or_perfil_critico": "ORC 76 x 6.4",
      "lrfd_contravientos_or_estado_control": "compresion",
      "lrfd_contravientos_or_pu_kN": 63.28065243928415,
      "lrfd_contravientos_or_pr_kN": 97.62016390432899,
      "lrfd_contravientos_or_tr_kN": 448.70611365,
      "lrfd_alertas": [
        "PLT controla al menos una viga IR con Cb=1.0 y Lb entre nodos; confirmar arriostramiento lateral real del patin comprimido antes de dictaminar el diseno final."
      ]
    },
    "fitness_detallado": [
      71584.01750959814,
      0.0010918951205383849,
      0.12335028497166003
    ],
    "rank": 1,
    "cumplimientos_norma": {
      "cumple_normativa": true,
      "cumple_dc": true,
      "dc_calculado": 0.7735649309222661,
      "dc_limite": 1.0,
      "cumple_deriva_servicio": true,
      "deriva_servicio_calculada": 0.0006294543334768043,
      "deriva_servicio_limite": 0.005,
      "util_deriva_servicio": 0.12589086669536087,
      "cumple_deriva_colapso": true,
      "deriva_colapso_calculada": 0.002797574815452464,
      "deriva_colapso_limite": 0.01,
      "util_deriva_colapso": 0.2797574815452464,
      "factor_inelastico_deriva": 4.444444444444445,
      "cumple_desplazamiento_azotea": true,
      "desplazamiento_azotea_calculado_m": 0.005102927554130818,
      "desplazamiento_azotea_limite_m": 0.1,
      "util_desplazamiento_azotea": 0.05102927554130818,
      "cumple_esbeltez": true,
      "esbeltez_kl_r_calculada": 33.11188870907426,
      "esbeltez_kl_r_limite": 200.0,
      "util_esbeltez": 0.16555944354537128,
      "cumple_cortante_basal": true,
      "cortante_basal_invalido": 0.0,
      "factor_escalamiento_cortante": 1.0,
      "requiere_escalamiento_cortante": false,
      "cumple_constructibilidad": true,
      "constructibilidad_total": 0.0,
      "cumple_espesor_minimo": true,
      "cumple_lrfd_local": true,
      "cumple_columna_mismo_perfil_altura": true,
      "cumple_telescopico": true,
      "cumple_ancho_nudo": true,
      "cumple_cfvd": true,
      "cumple_guillotina": true,
      "cumple_lrfd_detallado": true,
      "lrfd_max_util": 0.7933926972947388,
      "lrfd_penalizacion": 0.0,
      "lrfd_vigas_ir_no_cumplen": 0,
      "lrfd_columnas_or_no_cumplen": 0,
      "lrfd_contravientos_or_no_cumplen": 0
    },
    "factible": true,
    "perfiles_por_grupo": {
      "Columna_1": "ORC 305 x 15.9",
      "Columna_2": "ORC 254 x 15.9",
      "Viga_1": "IR 254 x 67.0",
      "Contraviento_1": "ORC 152 x 15.9",
      "Contraviento_2": "ORC 76 x 6.4",
      "Viga_2": "IR 203 x 26.8"
    }
  },
  {
    "genes": [
      122,
      118,
      45,
      105,
      51,
      45
    ],
    "perfiles": [
      "ORC 305 x 15.9",
      "ORC 254 x 15.9",
      "IR 254 x 67.0",
      "ORC 152 x 15.9",
      "ORC 76 x 6.4",
      "IR 254 x 67.0"
    ],
    "peso_kg": 77550.90350959815,
    "constructibilidad": {
      "lrfd_local": 0.0,
      "columna_mismo_perfil_altura": 0.0,
      "telescopico": 0.0,
      "ancho_nudo": 0.0,
      "total": 0.0
    },
    "penal_constructibilidad": 0.0,
    "penal_constructibilidad_letal": 0.0,
    "penal_embudo": 0.0,
    "guillotina": false,
    "fitness": [
      77550.90350959815,
      0.02873528520747256,
      0.0995842151494311
    ],
    "metricas": {
      "max_dc": 0.6643881180250697,
      "max_dc_combo": "SISMO_DOWN_1",
      "max_dc_elemento": 367,
      "max_dc_extremo": "i",
      "max_dc_tipo_revision": "OR biaxial simetrico: misma capacidad en ambos ejes locales",
      "max_dc_pu_N": 64852.26357959324,
      "max_dc_muy_Nm": 0.0,
      "max_dc_muz_Nm": 0.0,
      "max_dc_phi_pn_N": 97612.01595894003,
      "max_dc_phi_mny_Nm": 11596.096889999999,
      "max_dc_phi_mnz_Nm": 11596.096889999999,
      "max_dc_ratio_axial": 0.6643881180250697,
      "max_dc_ratio_my": 0.0,
      "max_dc_ratio_mz": 0.0,
      "max_dc_rama": "Pu/phiPn >= 0.20: Pu/phiPn + 8/9(My/phiMny + Mz/phiMnz)",
      "objetivo_dc_meta_util": 0.8,
      "objetivo_dc_max_util": 0.95,
      "cumple_objetivo_dc_max": true,
      "exceso_objetivo_dc": 0.0,
      "objetivo_dc_equilibrio": 0.02873528520747256,
      "max_deriva_elastica": 0.0006454936495512972,
      "max_deriva_combo": "SISMO_DOWN_1",
      "max_deriva_nivel": "Nivel 9.600000000000001 m",
      "util_servicio": 0.12909872991025945,
      "util_colapso": 0.2868860664672432,
      "desp_azotea_m": 0.005222103972100699,
      "desp_azotea_combo": "SISMO_DOWN_1",
      "util_azotea": 0.05222103972100699,
      "util_deriva": 0.2868860664672432,
      "objetivo_deriva_modo": "auto",
      "sistema_lateral": "arriostrado",
      "objetivo_deriva_min_util": 0.25,
      "objetivo_deriva_meta_util": 0.35,
      "cumple_objetivo_deriva_min": true,
      "deficit_objetivo_deriva": 0.0,
      "objetivo_deriva_equilibrio": 0.0995842151494311,
      "util_esbeltez": 0.16555944354537128,
      "esbeltez_elemento": 306,
      "esbeltez_kl_r": 33.11188870907426,
      "factor_cortante": 1.0,
      "factor_cortante_combo": "",
      "factor_cortante_direccion": "",
      "cortante_invalido": 0.0,
      "lrfd_detallado_activo": true,
      "lrfd_detallado_modo": "completo",
      "cumple_lrfd_detallado": true,
      "lrfd_max_util": 0.6643326643371611,
      "lrfd_penalizacion": 0.0,
      "lrfd_error": "",
      "lrfd_vigas_ir_total": 152,
      "lrfd_vigas_ir_no_cumplen": 0,
      "lrfd_vigas_ir_util_max": 0.2383147619463909,
      "lrfd_vigas_ir_elemento_critico": 330,
      "lrfd_vigas_ir_grupo_critico": "Viga_1",
      "lrfd_vigas_ir_perfil_critico": "IR 254 x 67.0",
      "lrfd_vigas_ir_estado_limite": "F",
      "lrfd_vigas_ir_mu_kN_m": 66.56260348606291,
      "lrfd_vigas_ir_mr_kN_m": 279.305415,
      "lrfd_columnas_or_total": 64,
      "lrfd_columnas_or_no_cumplen": 0,
      "lrfd_columnas_or_util_max": 0.3528683929443359,
      "lrfd_columnas_or_interaccion_max": 0.3528683929443359,
      "lrfd_columnas_or_elemento_critico": 106,
      "lrfd_columnas_or_grupo_critico": "Columna_2",
      "lrfd_columnas_or_perfil_critico": "ORC 254 x 15.9",
      "lrfd_columnas_or_combo_critico": "GRAV_DISEÑO",
      "lrfd_contravientos_or_total": 64,
      "lrfd_contravientos_or_no_cumplen": 0,
      "lrfd_contravientos_or_util_max": 0.6643326643371611,
      "lrfd_contravientos_or_elemento_critico": 367,
      "lrfd_contravientos_or_grupo_critico": "Contraviento_2",
      "lrfd_contravientos_or_perfil_critico": "ORC 76 x 6.4",
      "lrfd_contravientos_or_estado_control": "compresion",
      "lrfd_contravientos_or_pu_kN": 64.85226357959324,
      "lrfd_contravientos_or_pr_kN": 97.62016390432899,
      "lrfd_contravientos_or_tr_kN": 448.70611365,
      "lrfd_alertas": [
        "PLT controla al menos una viga IR con Cb=1.0 y Lb entre nodos; confirmar arriostramiento lateral real del patin comprimido antes de dictaminar el diseno final."
      ]
    },
    "fitness_detallado": [
      77550.90350959815,
      0.02873528520747256,
      0.0995842151494311
    ],
    "rank": 2,
    "cumplimientos_norma": {
      "cumple_normativa": true,
      "cumple_dc": true,
      "dc_calculado": 0.6643881180250697,
      "dc_limite": 1.0,
      "cumple_deriva_servicio": true,
      "deriva_servicio_calculada": 0.0006454936495512972,
      "deriva_servicio_limite": 0.005,
      "util_deriva_servicio": 0.12909872991025945,
      "cumple_deriva_colapso": true,
      "deriva_colapso_calculada": 0.002868860664672432,
      "deriva_colapso_limite": 0.01,
      "util_deriva_colapso": 0.2868860664672432,
      "factor_inelastico_deriva": 4.444444444444445,
      "cumple_desplazamiento_azotea": true,
      "desplazamiento_azotea_calculado_m": 0.005222103972100699,
      "desplazamiento_azotea_limite_m": 0.1,
      "util_desplazamiento_azotea": 0.05222103972100699,
      "cumple_esbeltez": true,
      "esbeltez_kl_r_calculada": 33.11188870907426,
      "esbeltez_kl_r_limite": 200.0,
      "util_esbeltez": 0.16555944354537128,
      "cumple_cortante_basal": true,
      "cortante_basal_invalido": 0.0,
      "factor_escalamiento_cortante": 1.0,
      "requiere_escalamiento_cortante": false,
      "cumple_constructibilidad": true,
      "constructibilidad_total": 0.0,
      "cumple_espesor_minimo": true,
      "cumple_lrfd_local": true,
      "cumple_columna_mismo_perfil_altura": true,
      "cumple_telescopico": true,
      "cumple_ancho_nudo": true,
      "cumple_cfvd": true,
      "cumple_guillotina": true,
      "cumple_lrfd_detallado": true,
      "lrfd_max_util": 0.6643326643371611,
      "lrfd_penalizacion": 0.0,
      "lrfd_vigas_ir_no_cumplen": 0,
      "lrfd_columnas_or_no_cumplen": 0,
      "lrfd_contravientos_or_no_cumplen": 0
    },
    "factible": true,
    "perfiles_por_grupo": {
      "Columna_1": "ORC 305 x 15.9",
      "Columna_2": "ORC 254 x 15.9",
      "Viga_1": "IR 254 x 67.0",
      "Contraviento_1": "ORC 152 x 15.9",
      "Contraviento_2": "ORC 76 x 6.4",
      "Viga_2": "IR 254 x 67.0"
    }
  }
]